ryft_sdk/__init__.py
ryft_sdk/_version.py
ryft_sdk/client.py
ryft_sdk/utils.py
ryft_sdk/webhook_signature_verifier.py
ryft_sdk/clients/__init__.py
ryft_sdk/clients/account_links.py
ryft_sdk/clients/accounts.py
ryft_sdk/clients/apple_pay.py
ryft_sdk/clients/customers.py
ryft_sdk/clients/disputes.py
ryft_sdk/clients/events.py
ryft_sdk/clients/files.py
ryft_sdk/clients/in_person_locations.py
ryft_sdk/clients/in_person_orders.py
ryft_sdk/clients/in_person_products.py
ryft_sdk/clients/in_person_skus.py
ryft_sdk/clients/in_person_terminals.py
ryft_sdk/clients/payment_methods.py
ryft_sdk/clients/payment_sessions.py
ryft_sdk/clients/payout_methods.py
ryft_sdk/clients/payouts.py
ryft_sdk/clients/persons.py
ryft_sdk/clients/platform_fees.py
ryft_sdk/clients/subscriptions.py
ryft_sdk/clients/transfers.py
ryft_sdk/clients/webhooks.py
ryft_sdk/models/__init__.py
ryft_sdk/models/address.py
ryft_sdk/models/deleted_resource_resp.py
ryft_sdk/models/errors.py
ryft_sdk/models/shipping_details.py
ryft_sdk/models/account_links/__init__.py
ryft_sdk/models/account_links/dto/__init__.py
ryft_sdk/models/account_links/dto/account_links.py
ryft_sdk/models/account_links/req/__init__.py
ryft_sdk/models/account_links/req/account_links_req.py
ryft_sdk/models/accounts/__init__.py
ryft_sdk/models/accounts/dto/__init__.py
ryft_sdk/models/accounts/dto/accounts.py
ryft_sdk/models/accounts/dto/payouts.py
ryft_sdk/models/accounts/req/__init__.py
ryft_sdk/models/accounts/req/accounts_req.py
ryft_sdk/models/accounts/req/authlink_req.py
ryft_sdk/models/accounts/req/payouts_req.py
ryft_sdk/models/apple_pay/__init__.py
ryft_sdk/models/apple_pay/dto/__init__.py
ryft_sdk/models/apple_pay/dto/apple_pay.py
ryft_sdk/models/apple_pay/req/__init__.py
ryft_sdk/models/apple_pay/req/apple_pay_req.py
ryft_sdk/models/customers/__init__.py
ryft_sdk/models/customers/dto/__init__.py
ryft_sdk/models/customers/dto/customers.py
ryft_sdk/models/customers/req/__init__.py
ryft_sdk/models/customers/req/customers_req.py
ryft_sdk-1.4.0.dist-info/licenses/LICENSE
ryft_sdk-1.4.0.dist-info/METADATA
ryft_sdk-1.4.0.dist-info/WHEEL
ryft_sdk-1.4.0.dist-info/top_level.txt
ryft_sdk-1.4.0.dist-info/RECORD
