Metadata-Version: 2.4
Name: ryft_sdk
Version: 1.4.0
Summary: Python SDK for Ryft API
Author-email: Ryft <tech@ryftpay.com>
Maintainer-email: Ryft <tech@ryftpay.com>
Project-URL: Homepage, https://ryftpay.com
Project-URL: Documentation, https://api-reference.ryftpay.com
Project-URL: Repository, https://github.com/ryftpay/ryft-python
Project-URL: Issues, https://github.com/ryftpay/ryft-python
Project-URL: Changelog, https://github.com/ryftpay/ryft-python
Project-URL: Bug Tracker, https://github.com/ryftpay/ryft-python/issues
Keywords: ryft,api,sdk
Classifier: Development Status :: 5 - Production/Stable
Classifier: Intended Audience :: Developers
Classifier: Topic :: Software Development :: Libraries :: Application Frameworks
Classifier: Programming Language :: Python :: 3
Classifier: Programming Language :: Python :: 3.6
Classifier: Programming Language :: Python :: 3.7
Classifier: Programming Language :: Python :: 3.8
Classifier: Programming Language :: Python :: 3.9
Classifier: Programming Language :: Python :: 3.10
Classifier: Programming Language :: Python :: 3.11
Classifier: Programming Language :: Python :: 3.12
Classifier: Programming Language :: Python :: 3.13
Requires-Python: >=3.6
License-File: LICENSE
Requires-Dist: requests
Requires-Dist: typing_extensions
Dynamic: license-file
